{
    "last_updated": "2026-03-25 16:44",
    "picks": [
        {
            "ticker": "AMZN",
            "price": 212.31,
            "score": 3,
            "reason": "Low RSI, Price Cross SMA20",
            "rsi": 42.4
        },
        {
            "ticker": "MSFT",
            "price": 371.35,
            "score": 2,
            "reason": "Deeply Oversold",
            "rsi": 11.7
        },
        {
            "ticker": "META",
            "price": 598.94,
            "score": 2,
            "reason": "Deeply Oversold",
            "rsi": 28.6
        },
        {
            "ticker": "NFLX",
            "price": 92.28,
            "score": 2,
            "reason": "Deeply Oversold",
            "rsi": 27.9
        }
    ]
}